dist_matrix/__init__.py
dist_matrix/cuda_dist_matrix.py
dist_matrix/cuda_dist_matrix_full.py
dist_matrix/meta.yaml
dist_matrix/njit_dist_matrix.py
dist_matrix/njit_dist_matrix_full.py
dist_matrix/tests/test_cpu_helper.py
dist_matrix/tests/test_dist_matrix.py
dist_matrix/tests/test_helper.py
dist_matrix/tests/test_njit.py
dist_matrix/utils/Timer.py
dist_matrix/utils/benchmark_njit.py
dist_matrix/utils/cpu_helper.py
dist_matrix/utils/cpu_metrics.py
dist_matrix/utils/helper.py
dist_matrix/utils/metrics.py
dist_matrix-1.0.4.dist-info/LICENSE
dist_matrix-1.0.4.dist-info/WHEEL
dist_matrix-1.0.4.dist-info/METADATA
dist_matrix-1.0.4.dist-info/RECORD
